setup.py
oktas_draw_libs/__init__.py
oktas_draw_libs/colors.py
oktas_draw_libs/example.py
oktas_draw_libs/game.py
oktas_draw_libs/gameobject.py
oktas_draw_libs/layer.py
oktas_draw_libs.egg-info/PKG-INFO
oktas_draw_libs.egg-info/SOURCES.txt
oktas_draw_libs.egg-info/dependency_links.txt
oktas_draw_libs.egg-info/not-zip-safe
oktas_draw_libs.egg-info/requires.txt
oktas_draw_libs.egg-info/top_level.txt