Metadata-Version: 1.0
Name: oktas-draw-libs
Version: 0.1.1
Summary: A simplified wrapper for pygame
Home-page: UNKNOWN
Author: Boris Biehl
Author-email: oktas_draw_libs@oktabyteprogramming.de
License: MIT
Platform: UNKNOWN
